bayes_positioner/LICENSE.txt
bayes_positioner/__init__.py
bayes_positioner/bayes_positioner.py
bayes_positioner-0.1.2.dist-info/LICENSE.txt
bayes_positioner-0.1.2.dist-info/METADATA
bayes_positioner-0.1.2.dist-info/WHEEL
bayes_positioner-0.1.2.dist-info/top_level.txt
bayes_positioner-0.1.2.dist-info/RECORD
