Metadata-Version: 2.2
Name: bayes_positioner
Version: 0.1.2
Summary: Bayesian time-difference-of-arrival positioning using PyMC
Home-page: https://github.com/pyscaffold/pyscaffold/
Author: CBeckwith
License: MIT
Project-URL: Documentation, https://pyscaffold.org/
Platform: any
Classifier: Development Status :: 4 - Beta
Classifier: Programming Language :: Python
License-File: LICENSE.txt
Requires-Dist: numpy
Requires-Dist: pymc
Requires-Dist: scipy
Requires-Dist: importlib-metadata; python_version < "3.8"
Provides-Extra: testing
Requires-Dist: setuptools; extra == "testing"
Requires-Dist: pytest; extra == "testing"
Requires-Dist: pytest-cov; extra == "testing"
